README.md
pyproject.toml
setup.cfg
setup.py
baseapp_ratings/__init__.py
baseapp_ratings.egg-info/PKG-INFO
baseapp_ratings.egg-info/SOURCES.txt
baseapp_ratings.egg-info/dependency_links.txt
baseapp_ratings.egg-info/requires.txt
baseapp_ratings.egg-info/top_level.txt
testproject/__init__.py
testproject/graphql.py
testproject/settings.py
testproject/setup.py
testproject/urls.py
testproject/wsgi.py
testproject/testapp/__init__.py
testproject/testapp/admin.py
testproject/testapp/apps.py
testproject/testapp/models.py
testproject/testapp/migrations/0001_initial.py
testproject/testapp/migrations/0002_user_is_ratings_enabled_user_ratings_average_and_more.py
testproject/testapp/migrations/0003_user_preferred_language.py
testproject/testapp/migrations/0004_user_profile.py
testproject/testapp/migrations/__init__.py